agent_client/__init__.py
agent_client/client.py
agent_client_cli/__init__.py
agent_client_cli/cli.py
agents_client-0.2.9.dist-info/licenses/LICENSE
agents_client-0.2.9.dist-info/METADATA
agents_client-0.2.9.dist-info/WHEEL
agents_client-0.2.9.dist-info/entry_points.txt
agents_client-0.2.9.dist-info/top_level.txt
agents_client-0.2.9.dist-info/RECORD
