Metadata-Version: 2.4
Name: agents-client
Version: 0.2.9
Summary: A comprehensive client library and CLI for interacting with the Agents API
Author-email: Levangie Laboratories <brayden@levangielaboratories.com>
License: Apache Software License
Project-URL: Homepage, https://github.com/Levangie-Laboratories/agents-client
Project-URL: Documentation, https://api.levangielaboratories.com/docs
Keywords: agents,api,client,chatbot,ai,cli
Classifier: Development Status :: 4 - Beta
Classifier: Intended Audience :: Developers
Classifier: License :: OSI Approved :: Apache Software License
Classifier: Programming Language :: Python :: 3.8
Classifier: Programming Language :: Python :: 3.9
Classifier: Programming Language :: Python :: 3.10
Classifier: Programming Language :: Python :: 3.11
Requires-Python: >=3.8
License-File: LICENSE
Requires-Dist: requests>=2.25.0
Requires-Dist: websockets>=10.0
Provides-Extra: cli
Requires-Dist: typer>=0.4.0; extra == "cli"
Requires-Dist: rich>=10.0.0; extra == "cli"
Requires-Dist: configparser>=5.0.0; extra == "cli"
Provides-Extra: dev
Requires-Dist: pytest>=6.0.0; extra == "dev"
Requires-Dist: pytest-asyncio>=0.18.0; extra == "dev"
Requires-Dist: black>=22.0.0; extra == "dev"
Requires-Dist: isort>=5.0.0; extra == "dev"
Requires-Dist: aiohttp>=3.8.0; extra == "dev"
Requires-Dist: python-dotenv>=0.19.0; extra == "dev"
Requires-Dist: pydantic>=1.8.0; extra == "dev"
Dynamic: license-file
